filetrace/__init__.py
filetrace/__main__.py
filetrace/_version.py
filetrace/cli.py
filetrace/test_all.py
filetrace/tracer.py
filetrace-0.0.4.dist-info/LICENSE
filetrace-0.0.4.dist-info/METADATA
filetrace-0.0.4.dist-info/WHEEL
filetrace-0.0.4.dist-info/entry_points.txt
filetrace-0.0.4.dist-info/top_level.txt
filetrace-0.0.4.dist-info/RECORD
