Metadata-Version: 2.1
Name: filetrace
Version: 0.0.4
Summary: Report files opened while executing a command
Home-page: https://github.com/joaompinto/filetrace
Author: João Pinto
Author-email: joao.pinto@vshn.ch
License: BSD-3
Platform: UNKNOWN
Requires-Dist: python-ptrace
